<Properties StartupConfiguration="{84C3B2D4-2E62-4AD5-A6F3-1507770B7DAA}|Default">
  <MonoDevelop.Ide.ItemProperties.LemonadeStand PreferredExecutionTarget="MonoDevelop.Default" />
  <MonoDevelop.Ide.Workbench ActiveDocument="LemonadeStand/Weather.cs">
    <Files>
      <File FileName="LemonadeStand/Program.cs" Line="13" Column="14" />
      <File FileName="LemonadeStand/Game.cs" Line="41" Column="35" />
      <File FileName="LemonadeStand/Player.cs" Line="134" Column="80" />
      <File FileName="LemonadeStand/Inventory.cs" Line="103" Column="10" />
      <File FileName="LemonadeStand/Day.cs" Line="63" Column="71" />
      <File FileName="LemonadeStand/Weather.cs" Line="69" Column="24" />
      <File FileName="LemonadeStand/Recipe.cs" Line="112" Column="40" />
      <File FileName="LemonadeStand/Customer.cs" Line="120" Column="45" />
      <File FileName="LemonadeStand/UserInterface.cs" Line="52" Column="38" />
      <File FileName="LemonadeStand/Ice.cs" Line="8" Column="10" />
    </Files>
  </MonoDevelop.Ide.Workbench>
  <MonoDevelop.Ide.Workspace ActiveConfiguration="Debug|x86" />
  <MonoDevelop.Ide.DebuggingService.Breakpoints>
    <BreakpointStore />
  </MonoDevelop.Ide.DebuggingService.Breakpoints>
  <MonoDevelop.Ide.DebuggingService.PinnedWatches />
  <MultiItemStartupConfigurations />
</Properties>